Metadata-Version: 2.1
Name: torchtnt-nightly
Version: 2024.8.1
Summary: A lightweight library for PyTorch training tools and utilities
Home-page: https://github.com/pytorch/tnt
Author: PyTorch
Author-email: daniellepintz@fb.com
License: BSD-3
Keywords: pytorch,torch,training,tools,utilities
Classifier: Development Status :: 2 - Pre-Alpha
Classifier: Intended Audience :: Developers
Classifier: Intended Audience :: Science/Research
Classifier: License :: OSI Approved :: BSD License
Classifier: Programming Language :: Python :: 3
Classifier: Programming Language :: Python :: 3.7
Classifier: Topic :: Scientific/Engineering :: Artificial Intelligence
Requires-Python: >=3.7
License-File: LICENSE
Requires-Dist: torch
Requires-Dist: numpy ==1.24.4
Requires-Dist: fsspec
Requires-Dist: tensorboard
Requires-Dist: packaging
Requires-Dist: psutil
Requires-Dist: pyre-extensions
Requires-Dist: typing-extensions
Requires-Dist: setuptools
Requires-Dist: tqdm
Requires-Dist: tabulate
Provides-Extra: dev
Requires-Dist: parameterized ; extra == 'dev'
Requires-Dist: pytest ; extra == 'dev'
Requires-Dist: pytest-cov ; extra == 'dev'
Requires-Dist: torchsnapshot-nightly ; extra == 'dev'
Requires-Dist: pyre-check ; extra == 'dev'
Requires-Dist: torchvision ==0.15.2 ; extra == 'dev'
